{"stat.useItem.35":8,"stat.useItem.19":1,"stat.useItem.323":16,"stat.useItem.85":1,"achievement.openInventory":67,"stat.useItem.145":2,"stat.jump":770,"achievement.exploreAllBiomes":{"value":0,"progress":["Forest","Desert","DesertHills","Deep Ocean","Ocean","Birch Forest","Beach","Plains","Roofed Forest","River","Birch Forest Hills","ForestHills"]},"stat.mobKills":1,"stat.useItem.3":2,"stat.useItem.4":12,"stat.useItem.5":1,"stat.useItem.383":2,"stat.useItem.108":1,"stat.useItem.50":3,"stat.useItem.76":3,"stat.killEntity.Villager":1,"stat.damageDealt":200,"stat.useItem.126":2,"stat.useItem.171":4,"stat.useItem.12":8,"stat.useItem.101":2,"stat.useItem.95":112,"stat.useItem.259":1,"stat.drop":3,"stat.useItem.24":2,"stat.useItem.134":1,"stat.flyOneCm":3111524,"stat.useItem.152":14,"stat.leaveGame":3,"stat.useItem.155":12,"stat.useItem.98":16,"stat.useItem.175":1,"stat.useItem.331":163,"stat.useItem.354":3,"stat.walkOneCm":1128305,"stat.diveOneCm":28066,"stat.swimOneCm":23870,"stat.useItem.42":2,"stat.useItem.160":2,"stat.playOneMinute":242966}