{
  "attackIndex": 466,
  "attackName": "Captivate",
  "attackType": "Normal",
  "attackCategory": "STATUS",
  "basePower": 0,
  "ppBase": 20,
  "ppMax": 32,
  "accuracy": 100,
  "makesContact": false,
  "effects": [
    {
      "modifiers": [],
      "persists": false,
      "effectTypeID": "Captivate"
    }
  ],
  "animations": [
    "leapForward"
  ],
  "targetingInfo": {
    "hitsAll": true,
    "hitsOppositeFoe": true,
    "hitsAdjacentFoe": true,
    "hitsExtendedFoe": false,
    "hitsSelf": false,
    "hitsAdjacentAlly": false,
    "hitsExtendedAlly": false
  }
}