{
  "attackIndex": 601,
  "attackName": "Oblivion Wing",
  "attackType": "Flying",
  "attackCategory": "SPECIAL",
  "basePower": 80,
  "ppBase": 10,
  "ppMax": 16,
  "accuracy": 100,
  "makesContact": false,
  "effects": [
    {
      "drainPercent": 75,
      "modifiers": [],
      "persists": false,
      "effectTypeID": "Drain"
    }
  ],
  "animations": [
    "leapForward"
  ],
  "targetingInfo": {
    "hitsAll": false,
    "hitsOppositeFoe": true,
    "hitsAdjacentFoe": true,
    "hitsExtendedFoe": true,
    "hitsSelf": false,
    "hitsAdjacentAlly": true,
    "hitsExtendedAlly": true
  }
}